gtfs_railways/__init__.py
gtfs_railways/utils.py
gtfs_railways/w1.py
gtfs_railways/w2.py
gtfs_railways-0.1.3.dist-info/METADATA
gtfs_railways-0.1.3.dist-info/WHEEL
gtfs_railways-0.1.3.dist-info/top_level.txt
gtfs_railways-0.1.3.dist-info/RECORD
