Metadata-Version: 2.1
Name: gtfs_railways
Version: 0.1.3
Summary: Functions to work on GTFS railways data
Home-page: https://github.com/Praneesh-Sharma
Author: Praneesh Sharma
Author-email: praneesh.sharma@dtsc.be
Requires-Python: >=3.6
Requires-Dist: pandas
Requires-Dist: numpy
Requires-Dist: bokeh
Requires-Dist: networkx
Requires-Dist: matplotlib
Requires-Dist: geopy
Requires-Dist: thefuzz
Requires-Dist: gtfspy
Requires-Dist: ipython
